LICENSE
README.md
pyproject.toml
setup.cfg
setup.py
gadapt/__init__.py
gadapt/ga.py
gadapt.egg-info/PKG-INFO
gadapt.egg-info/SOURCES.txt
gadapt.egg-info/dependency_links.txt
gadapt.egg-info/requires.txt
gadapt.egg-info/top_level.txt
gadapt/adapters/__init__.py
gadapt/adapters/ga_logging/__init__.py
gadapt/adapters/ga_logging/logging_settings.py
gadapt/adapters/string_operation/__init__.py
gadapt/adapters/string_operation/ga_strings.py
gadapt/adapters/validation/__init__.py
gadapt/adapters/validation/base_options_validator.py
gadapt/adapters/validation/common_options_validator.py
gadapt/execution/__init__.py
gadapt/execution/ga_executor.py
gadapt/factory/__init__.py
gadapt/factory/ga_base_factory.py
gadapt/factory/ga_factory.py
gadapt/ga_model/__init__.py
gadapt/ga_model/allele.py
gadapt/ga_model/chromosome.py
gadapt/ga_model/definitions.py
gadapt/ga_model/ga_options.py
gadapt/ga_model/ga_results.py
gadapt/ga_model/gene.py
gadapt/ga_model/message_levels.py
gadapt/ga_model/population.py
gadapt/ga_model/ranking_model.py
gadapt/operations/__init__.py
gadapt/operations/chromosome_update/__init__.py
gadapt/operations/chromosome_update/base_chromosome_updater.py
gadapt/operations/chromosome_update/parent_diversity_chromosome_updater.py
gadapt/operations/cost_finding/__init__.py
gadapt/operations/cost_finding/base_cost_finder.py
gadapt/operations/cost_finding/elitism_cost_finder.py
gadapt/operations/crossover/__init__.py
gadapt/operations/crossover/base_crossover.py
gadapt/operations/crossover/blending_crossover.py
gadapt/operations/crossover/uniform_crossover.py
gadapt/operations/exit_check/__init__.py
gadapt/operations/exit_check/avg_cost_exit_checker.py
gadapt/operations/exit_check/base_exit_checker.py
gadapt/operations/exit_check/min_cost_exit_checker.py
gadapt/operations/exit_check/number_of_generations_exit_checker.py
gadapt/operations/exit_check/requested_cost_exit_checker.py
gadapt/operations/gene_update/__init__.py
gadapt/operations/gene_update/base_gene_updater.py
gadapt/operations/gene_update/cross_diversity_gene_updater.py
gadapt/operations/immigration/__init__.py
