Metadata-Version: 2.1
Name: gadapt
Version: 0.4.21
Summary: GAdapt: A Python Library for        Self-Adaptive Genetic Algorithm.
Home-page: https://github.com/bpzoran/gadapt
Author: Zoran Jankovic
Author-email: bpzoran@yahoo.com
License-File: LICENSE
Requires-Dist: numpy==1.26.4
